reComputer/__init__.py
reComputer/main.py
reComputer/scripts/check.sh
reComputer/scripts/clean.sh
reComputer/scripts/run.sh
reComputer/scripts/update.sh
reComputer/scripts/utils.sh
reComputer/scripts/MoveNet-Lightning/clean.sh
reComputer/scripts/MoveNet-Lightning/getVersion.sh
reComputer/scripts/MoveNet-Lightning/init.sh
reComputer/scripts/MoveNet-Lightning/readme.md
reComputer/scripts/MoveNet-Lightning/run.sh
reComputer/scripts/MoveNet-Thunder/clean.sh
reComputer/scripts/MoveNet-Thunder/getVersion.sh
reComputer/scripts/MoveNet-Thunder/init.sh
reComputer/scripts/MoveNet-Thunder/readme.md
reComputer/scripts/MoveNet-Thunder/run.sh
reComputer/scripts/MoveNetJS/clean.sh
reComputer/scripts/MoveNetJS/readme.md
reComputer/scripts/MoveNetJS/run.sh
reComputer/scripts/Sheared-LLaMA-2.7B-ShareGPT/config.yaml
reComputer/scripts/Sheared-LLaMA-2.7B-ShareGPT/init.sh
reComputer/scripts/Sheared-LLaMA-2.7B-ShareGPT/run.sh
reComputer/scripts/audiocraft/README.md
reComputer/scripts/audiocraft/clean.sh
reComputer/scripts/audiocraft/config.yaml
reComputer/scripts/audiocraft/init.sh
reComputer/scripts/audiocraft/run.sh
reComputer/scripts/comfyui/LICENSE
reComputer/scripts/comfyui/README.md
reComputer/scripts/comfyui/clean.sh
reComputer/scripts/comfyui/config.yaml
reComputer/scripts/comfyui/init.sh
reComputer/scripts/comfyui/run.sh
reComputer/scripts/deep-live-cam/Dockerfile
reComputer/scripts/deep-live-cam/LICENSE
reComputer/scripts/deep-live-cam/README.md
reComputer/scripts/deep-live-cam/clean.sh
reComputer/scripts/deep-live-cam/config.yaml
reComputer/scripts/deep-live-cam/init.sh
reComputer/scripts/deep-live-cam/run.sh
reComputer/scripts/depth-anything/Dockerfile
reComputer/scripts/depth-anything/LICENSE
reComputer/scripts/depth-anything/README.md
reComputer/scripts/depth-anything/clean.sh
reComputer/scripts/depth-anything/config.yaml
reComputer/scripts/depth-anything/init.sh
reComputer/scripts/depth-anything/run.sh
reComputer/scripts/depth-anything-v2/Dockerfile
jetson_examples-0.2.4.dist-info/LICENSE
jetson_examples-0.2.4.dist-info/METADATA
jetson_examples-0.2.4.dist-info/WHEEL
jetson_examples-0.2.4.dist-info/entry_points.txt
jetson_examples-0.2.4.dist-info/top_level.txt
jetson_examples-0.2.4.dist-info/RECORD
