Metadata-Version: 2.2
Name: jetson-examples
Version: 0.2.4
Summary: Running Gen AI models and applications on NVIDIA Jetson devices with one-line command
Author-email: luozhixin <zhixin.luo@seeed.cc>
Project-URL: Homepage, https://github.com/Seeed-Projects/jetson-examples
Project-URL: Issues, https://github.com/Seeed-Projects/jetson-examples/issues
Keywords: llama,llava,gpt,llm,nvidia,jetson,multimodal,jetson orin
Classifier: Programming Language :: Python :: 3
Classifier: License :: OSI Approved :: MIT License
Classifier: Operating System :: OS Independent
Requires-Python: >=3.8
License-File: LICENSE
